odoo/addons/hr_holidays_leave_repeated/README.rst
odoo/addons/hr_holidays_leave_repeated/__init__.py
odoo/addons/hr_holidays_leave_repeated/__manifest__.py
odoo/addons/hr_holidays_leave_repeated/i18n/fr.po
odoo/addons/hr_holidays_leave_repeated/i18n/hr_holidays_leave_repeated.pot
odoo/addons/hr_holidays_leave_repeated/i18n/nl.po
odoo/addons/hr_holidays_leave_repeated/models/__init__.py
odoo/addons/hr_holidays_leave_repeated/models/hr_leave.py
odoo/addons/hr_holidays_leave_repeated/models/hr_leave_type.py
odoo/addons/hr_holidays_leave_repeated/readme/CONFIGURE.rst
odoo/addons/hr_holidays_leave_repeated/readme/CONTRIBUTORS.rst
odoo/addons/hr_holidays_leave_repeated/readme/DESCRIPTION.rst
odoo/addons/hr_holidays_leave_repeated/readme/USAGE.rst
odoo/addons/hr_holidays_leave_repeated/static/description/icon.png
odoo/addons/hr_holidays_leave_repeated/static/description/index.html
odoo/addons/hr_holidays_leave_repeated/tests/__init__.py
odoo/addons/hr_holidays_leave_repeated/tests/test_holidays_leave_repeated.py
odoo/addons/hr_holidays_leave_repeated/views/hr_leave.xml
odoo/addons/hr_holidays_leave_repeated/views/hr_leave_type.xml
odoo12_addon_hr_holidays_leave_repeated-12.0.1.0.1.dist-info/METADATA
odoo12_addon_hr_holidays_leave_repeated-12.0.1.0.1.dist-info/WHEEL
odoo12_addon_hr_holidays_leave_repeated-12.0.1.0.1.dist-info/top_level.txt
odoo12_addon_hr_holidays_leave_repeated-12.0.1.0.1.dist-info/RECORD
